jadio_encryption_vault/__init__.py
jadio_encryption_vault/ai/__init__.py
jadio_encryption_vault/cli/__init__.py
jadio_encryption_vault/cli/clicommands.json
jadio_encryption_vault/cli/main.py
jadio_encryption_vault/core/__init__.py
jadio_encryption_vault-0.0.1.dist-info/METADATA
jadio_encryption_vault-0.0.1.dist-info/WHEEL
jadio_encryption_vault-0.0.1.dist-info/licenses/LICENSE
jadio_encryption_vault-0.0.1.dist-info/RECORD
